squidtools/__init__.py
squidtools/gpt_utils.py
squidtools/gpt_utils_async.py
squidtools/linkedin.py
squidtools/muckrack.py
squidtools/names.py
squidtools/proquest.py
squidtools/qualtrics.py
squidtools/robust_task.py
squidtools/selenium_helpers.py
squidtools/sqllm.py
squidtools/strings.py
squidtools/util.py
squidtools/webscraper.py
squidtools/workflow.py
squidtools-0.0.12.data/scripts/sqllm-apply
squidtools-0.0.12.dist-info/METADATA
squidtools-0.0.12.dist-info/WHEEL
squidtools-0.0.12.dist-info/top_level.txt
squidtools-0.0.12.dist-info/RECORD
